{
    "camera_heartbeat_freq": 10.0,
    "depth_heartbeat_freq": 10.0,
    "image_enhancement_heartbeat_freq": 10.0,
    "sensor_fusion_heartbeat_freq": 10.0,
    "segmentation_heartbeat_freq": 10.0,
    "rgb_camera_freq": 10.0,
    "rgb_enhanced_freq": 10.0,
    "segmentation_freq": 10.0,
    "sensors_fused_freq": 10.0,
    "depth_camera_freq": 10.0,
    "camera_heartbeat_status": 0,
    "depth_heartbeat_status": 0,
    "image_enhancement_heartbeat_status": 0,
    "sensor_fusion_heartbeat_status": 0,
    "segmentation_heartbeat_status": 0,
    "camera_lc_state": 0,
    "lidar_lc_state": 0,
    "image_enhancement_lc_state": 0,
    "sensor_fusion_lc_state": 0,
    "segmentation_lc_state": 0,
    "current_phase": 0,
    "image_degraded": false
}